merlion/plot.py
merlion/dashboard/__init__.py
merlion/dashboard/__main__.py
merlion/dashboard/server.py
merlion/dashboard/settings.py
merlion/dashboard/assets/Acumin-BdPro.otf
merlion/dashboard/assets/base.css
merlion/dashboard/assets/merlion.css
merlion/dashboard/assets/merlion_small.svg
merlion/dashboard/assets/modal.css
merlion/dashboard/assets/resizing.js
merlion/dashboard/assets/styles.css
merlion/dashboard/assets/upload.svg
merlion/dashboard/assets/fonts/SalesforceSans-Bold.woff
merlion/dashboard/assets/fonts/SalesforceSans-BoldItalic.woff
merlion/dashboard/assets/fonts/SalesforceSans-Italic.woff
merlion/dashboard/assets/fonts/SalesforceSans-Light.woff
merlion/dashboard/assets/fonts/SalesforceSans-LightItalic.woff
merlion/dashboard/assets/fonts/SalesforceSans-Regular.woff
merlion/dashboard/assets/fonts/SalesforceSans-Thin.woff
merlion/dashboard/assets/fonts/SalesforceSans-ThinItalic.woff
merlion/dashboard/callbacks/__init__.py
merlion/dashboard/callbacks/anomaly.py
merlion/dashboard/callbacks/data.py
merlion/dashboard/callbacks/forecast.py
merlion/dashboard/models/__init__.py
merlion/dashboard/models/anomaly.py
merlion/dashboard/models/data.py
merlion/dashboard/models/forecast.py
merlion/dashboard/models/utils.py
merlion/dashboard/pages/__init__.py
merlion/dashboard/pages/anomaly.py
merlion/dashboard/pages/data.py
merlion/dashboard/pages/forecast.py
merlion/dashboard/pages/utils.py
merlion/dashboard/utils/__init__.py
merlion/dashboard/utils/file_manager.py
merlion/dashboard/utils/layout.py
merlion/dashboard/utils/log.py
merlion/dashboard/utils/plot.py
merlion/evaluate/anomaly.py
merlion/evaluate/base.py
merlion/evaluate/forecast.py
merlion/models/base.py
merlion/models/deep_base.py
merlion/models/defaults.py
merlion/models/factory.py
merlion/models/layers.py
merlion/models/anomaly/__init__.py
merlion/models/anomaly/autoencoder.py
merlion/models/anomaly/base.py
merlion/models/anomaly/dagmm.py
merlion/models/anomaly/dbl.py
salesforce_merlion-2.0.4.dist-info/AUTHORS.md
salesforce_merlion-2.0.4.dist-info/LICENSE
salesforce_merlion-2.0.4.dist-info/METADATA
salesforce_merlion-2.0.4.dist-info/WHEEL
salesforce_merlion-2.0.4.dist-info/top_level.txt
salesforce_merlion-2.0.4.dist-info/RECORD
