Metadata-Version: 2.1
Name: salesforce-merlion
Version: 2.0.4
Summary: Merlion: A Machine Learning Framework for Time Series Intelligence
Home-page: https://github.com/salesforce/Merlion
Author: Aadyot Bhatnagar, Paul Kassianik, Chenghao Liu, Tian Lan, Wenzhuo Yang, Rowan Cassius, Doyen Sahoo, Devansh Arpit, Sri Subramanian, Gerald Woo, Amrita Saha, Arun Kumar Jagota, Gokulakrishnan Gopalakrishnan, Manpreet Singh, K C Krithika, Sukumar Maddineni, Daeki Cho, Bo Zong, Yingbo Zhou, Caiming Xiong, Silvio Savarese, Steven Hoi, Huan Wang
Author-email: abhatnagar@salesforce.com
License: 3-Clause BSD
Keywords: time series,forecasting,anomaly detection,machine learning,autoML,ensemble learning,benchmarking,Python,scientific toolkit
Requires-Python: >=3.7.0
License-File: LICENSE
License-File: AUTHORS.md
Requires-Dist: cython
Requires-Dist: dill
Requires-Dist: GitPython
Requires-Dist: py4j
Requires-Dist: matplotlib
Requires-Dist: plotly >=4.13
Requires-Dist: numpy <2.0,>=1.21
Requires-Dist: packaging
Requires-Dist: pandas >=1.1.0
Requires-Dist: prophet >=1.1
Requires-Dist: scikit-learn >=0.22
Requires-Dist: scipy >=1.6.0
Requires-Dist: statsmodels >=0.12.2
Requires-Dist: lightgbm
Requires-Dist: tqdm
Provides-Extra: all
Requires-Dist: dash[diskcache] >=2.4 ; extra == 'all'
Requires-Dist: dash-bootstrap-components >=1.0 ; extra == 'all'
Requires-Dist: diskcache ; extra == 'all'
Requires-Dist: torch >=1.9.0 ; extra == 'all'
Requires-Dist: einops >=0.4.0 ; extra == 'all'
Requires-Dist: pyspark[sql] >=3 ; extra == 'all'
Provides-Extra: dashboard
Requires-Dist: dash[diskcache] >=2.4 ; extra == 'dashboard'
Requires-Dist: dash-bootstrap-components >=1.0 ; extra == 'dashboard'
Requires-Dist: diskcache ; extra == 'dashboard'
Provides-Extra: deep-learning
Requires-Dist: torch >=1.9.0 ; extra == 'deep-learning'
Requires-Dist: einops >=0.4.0 ; extra == 'deep-learning'
Provides-Extra: spark
Requires-Dist: pyspark[sql] >=3 ; extra == 'spark'
